{
  "1": [
    {
      "word": "تَبَٰرَكَ",
      "start": 0.26,
      "end": 1.45
    },
    {
      "word": "ٱلَّذِى",
      "start": 1.45,
      "end": 2.63
    },
    {
      "word": "بِيَدِهِ",
      "start": 2.63,
      "end": 3.82
    },
    {
      "word": "ٱلْمُلْكُ",
      "start": 3.82,
      "end": 5.01
    },
    {
      "word": "وَهُوَ",
      "start": 5.01,
      "end": 6.19
    },
    {
      "word": "عَلَىٰ",
      "start": 6.19,
      "end": 7.38
    },
    {
      "word": "كُلِّ",
      "start": 7.38,
      "end": 8.57
    },
    {
      "word": "شَىْءٍ",
      "start": 8.57,
      "end": 9.75
    },
    {
      "word": "قَدِيرٌ",
      "start": 9.75,
      "end": 10.94
    }
  ],
  "2": [
    {
      "word": "ٱلَّذِى",
      "start": 0,
      "end": 1.36
    },
    {
      "word": "خَلَقَ",
      "start": 1.36,
      "end": 2.72
    },
    {
      "word": "ٱلْمَوْتَ",
      "start": 2.72,
      "end": 4.08
    },
    {
      "word": "وَٱلْحَيَوٰةَ",
      "start": 4.08,
      "end": 5.44
    },
    {
      "word": "لِيَبْلُوَكُمْ",
      "start": 5.44,
      "end": 6.8
    },
    {
      "word": "أَيُّكُمْ",
      "start": 6.8,
      "end": 8.16
    },
    {
      "word": "أَحْسَنُ",
      "start": 8.16,
      "end": 9.52
    },
    {
      "word": "عَمَلًا",
      "start": 9.52,
      "end": 10.88
    },
    {
      "word": "وَهُوَ",
      "start": 10.88,
      "end": 12.24
    },
    {
      "word": "ٱلْعَزِيزُ",
      "start": 12.24,
      "end": 13.6
    },
    {
      "word": "ٱلْغَفُورُ",
      "start": 13.6,
      "end": 14.96
    }
  ],
  "3": [
    {
      "word": "ٱلَّذِى",
      "start": 0.1,
      "end": 1.2
    },
    {
      "word": "خَلَقَ",
      "start": 1.2,
      "end": 2.3
    },
    {
      "word": "سَبْعَ",
      "start": 2.3,
      "end": 3.4
    },
    {
      "word": "سَمَٰوَٰتٍ",
      "start": 3.4,
      "end": 4.5
    },
    {
      "word": "طِبَاقًا",
      "start": 4.5,
      "end": 5.61
    },
    {
      "word": "مَّا",
      "start": 5.61,
      "end": 6.71
    },
    {
      "word": "تَرَىٰ",
      "start": 6.71,
      "end": 7.81
    },
    {
      "word": "فِى",
      "start": 7.81,
      "end": 8.91
    },
    {
      "word": "خَلْقِ",
      "start": 8.91,
      "end": 10.01
    },
    {
      "word": "ٱلرَّحْمَٰنِ",
      "start": 10.01,
      "end": 11.11
    },
    {
      "word": "مِن",
      "start": 11.11,
      "end": 12.21
    },
    {
      "word": "تَفَٰوُتٍ",
      "start": 12.21,
      "end": 13.31
    },
    {
      "word": "فَٱرْجِعِ",
      "start": 13.31,
      "end": 14.41
    },
    {
      "word": "ٱلْبَصَرَ",
      "start": 14.41,
      "end": 15.52
    },
    {
      "word": "هَلْ",
      "start": 15.52,
      "end": 16.62
    },
    {
      "word": "تَرَىٰ",
      "start": 16.62,
      "end": 17.72
    },
    {
      "word": "مِن",
      "start": 17.72,
      "end": 18.82
    },
    {
      "word": "فُطُورٍ",
      "start": 18.82,
      "end": 19.92
    }
  ],
  "4": [
    {
      "word": "ثُمَّ",
      "start": 0,
      "end": 1.13
    },
    {
      "word": "ٱرْجِعِ",
      "start": 1.13,
      "end": 2.26
    },
    {
      "word": "ٱلْبَصَرَ",
      "start": 2.26,
      "end": 3.4
    },
    {
      "word": "كَرَّتَيْنِ",
      "start": 3.4,
      "end": 4.53
    },
    {
      "word": "يَنقَلِبْ",
      "start": 4.53,
      "end": 5.66
    },
    {
      "word": "إِلَيْكَ",
      "start": 5.66,
      "end": 6.79
    },
    {
      "word": "ٱلْبَصَرُ",
      "start": 6.79,
      "end": 7.92
    },
    {
      "word": "خَاسِئًا",
      "start": 7.92,
      "end": 9.06
    },
    {
      "word": "وَهُوَ",
      "start": 9.06,
      "end": 10.19
    },
    {
      "word": "حَسِيرٌ",
      "start": 10.19,
      "end": 11.32
    }
  ],
  "5": [
    {
      "word": "وَلَقَدْ",
      "start": 0,
      "end": 1.65
    },
    {
      "word": "زَيَّنَّا",
      "start": 1.65,
      "end": 3.3
    },
    {
      "word": "ٱلسَّمَآءَ",
      "start": 3.3,
      "end": 4.95
    },
    {
      "word": "ٱلدُّنْيَا",
      "start": 4.95,
      "end": 6.59
    },
    {
      "word": "بِمَصَٰبِيحَ",
      "start": 6.59,
      "end": 8.24
    },
    {
      "word": "وَجَعَلْنَٰهَا",
      "start": 8.24,
      "end": 9.89
    },
    {
      "word": "رُجُومًا",
      "start": 9.89,
      "end": 11.54
    },
    {
      "word": "لِّلشَّيَٰطِينِ",
      "start": 11.54,
      "end": 13.19
    },
    {
      "word": "وَأَعْتَدْنَا",
      "start": 13.19,
      "end": 14.84
    },
    {
      "word": "لَهُمْ",
      "start": 14.84,
      "end": 16.48
    },
    {
      "word": "عَذَابَ",
      "start": 16.48,
      "end": 18.13
    },
    {
      "word": "ٱلسَّعِيرِ",
      "start": 18.13,
      "end": 19.78
    }
  ],
  "6": [
    {
      "word": "وَلِلَّذِينَ",
      "start": 0,
      "end": 1.33
    },
    {
      "word": "كَفَرُوا۟",
      "start": 1.33,
      "end": 2.67
    },
    {
      "word": "بِرَبِّهِمْ",
      "start": 2.67,
      "end": 4
    },
    {
      "word": "عَذَابُ",
      "start": 4,
      "end": 5.34
    },
    {
      "word": "جَهَنَّمَ",
      "start": 5.34,
      "end": 6.67
    },
    {
      "word": "وَبِئْسَ",
      "start": 6.67,
      "end": 8.01
    },
    {
      "word": "ٱلْمَصِيرُ",
      "start": 8.01,
      "end": 9.34
    }
  ],
  "7": [
    {
      "word": "إِذَآ",
      "start": 0,
      "end": 1.13
    },
    {
      "word": "أُلْقُوا۟",
      "start": 1.13,
      "end": 2.25
    },
    {
      "word": "فِيهَا",
      "start": 2.25,
      "end": 3.38
    },
    {
      "word": "سَمِعُوا۟",
      "start": 3.38,
      "end": 4.5
    },
    {
      "word": "لَهَا",
      "start": 4.5,
      "end": 5.63
    },
    {
      "word": "شَهِيقًا",
      "start": 5.63,
      "end": 6.75
    },
    {
      "word": "وَهِىَ",
      "start": 6.75,
      "end": 7.88
    },
    {
      "word": "تَفُورُ",
      "start": 7.88,
      "end": 9
    }
  ],
  "8": [
    {
      "word": "تَكَادُ",
      "start": 0,
      "end": 1.24
    },
    {
      "word": "تَمَيَّزُ",
      "start": 1.24,
      "end": 2.49
    },
    {
      "word": "مِنَ",
      "start": 2.49,
      "end": 3.73
    },
    {
      "word": "ٱلْغَيْظِ",
      "start": 3.73,
      "end": 4.97
    },
    {
      "word": "كُلَّمَآ",
      "start": 4.97,
      "end": 6.22
    },
    {
      "word": "أُلْقِىَ",
      "start": 6.22,
      "end": 7.46
    },
    {
      "word": "فِيهَا",
      "start": 7.46,
      "end": 8.7
    },
    {
      "word": "فَوْجٌ",
      "start": 8.7,
      "end": 9.94
    },
    {
      "word": "سَأَلَهُمْ",
      "start": 9.94,
      "end": 11.19
    },
    {
      "word": "خَزَنَتُهَآ",
      "start": 11.19,
      "end": 12.43
    },
    {
      "word": "أَلَمْ",
      "start": 12.43,
      "end": 13.67
    },
    {
      "word": "يَأْتِكُمْ",
      "start": 13.67,
      "end": 14.92
    },
    {
      "word": "نَذِيرٌ",
      "start": 14.92,
      "end": 16.16
    }
  ],
  "9": [
    {
      "word": "قَالُوا۟",
      "start": 0,
      "end": 1.21
    },
    {
      "word": "بَلَىٰ",
      "start": 1.21,
      "end": 2.42
    },
    {
      "word": "قَدْ",
      "start": 2.42,
      "end": 3.64
    },
    {
      "word": "جَآءَنَا",
      "start": 3.64,
      "end": 4.85
    },
    {
      "word": "نَذِيرٌ",
      "start": 4.85,
      "end": 6.06
    },
    {
      "word": "فَكَذَّبْنَا",
      "start": 6.06,
      "end": 7.27
    },
    {
      "word": "وَقُلْنَا",
      "start": 7.27,
      "end": 8.49
    },
    {
      "word": "مَا",
      "start": 8.49,
      "end": 9.7
    },
    {
      "word": "نَزَّلَ",
      "start": 9.7,
      "end": 10.91
    },
    {
      "word": "ٱللَّهُ",
      "start": 10.91,
      "end": 12.12
    },
    {
      "word": "مِن",
      "start": 12.12,
      "end": 13.33
    },
    {
      "word": "شَىْءٍ",
      "start": 13.33,
      "end": 14.55
    },
    {
      "word": "إِنْ",
      "start": 14.55,
      "end": 15.76
    },
    {
      "word": "أَنتُمْ",
      "start": 15.76,
      "end": 16.97
    },
    {
      "word": "إِلَّا",
      "start": 16.97,
      "end": 18.18
    },
    {
      "word": "فِى",
      "start": 18.18,
      "end": 19.4
    },
    {
      "word": "ضَلَٰلٍ",
      "start": 19.4,
      "end": 20.61
    },
    {
      "word": "كَبِيرٍ",
      "start": 20.61,
      "end": 21.82
    }
  ],
  "10": [
    {
      "word": "وَقَالُوا۟",
      "start": 0,
      "end": 0.93
    },
    {
      "word": "لَوْ",
      "start": 0.93,
      "end": 1.86
    },
    {
      "word": "كُنَّا",
      "start": 1.86,
      "end": 2.79
    },
    {
      "word": "نَسْمَعُ",
      "start": 2.79,
      "end": 3.72
    },
    {
      "word": "أَوْ",
      "start": 3.72,
      "end": 4.65
    },
    {
      "word": "نَعْقِلُ",
      "start": 4.65,
      "end": 5.57
    },
    {
      "word": "مَا",
      "start": 5.57,
      "end": 6.5
    },
    {
      "word": "كُنَّا",
      "start": 6.5,
      "end": 7.43
    },
    {
      "word": "فِىٓ",
      "start": 7.43,
      "end": 8.36
    },
    {
      "word": "أَصْحَٰبِ",
      "start": 8.36,
      "end": 9.29
    },
    {
      "word": "ٱلسَّعِيرِ",
      "start": 9.29,
      "end": 10.22
    }
  ],
  "11": [
    {
      "word": "فَٱعْتَرَفُوا۟",
      "start": 0,
      "end": 1.5
    },
    {
      "word": "بِذَنۢبِهِمْ",
      "start": 1.5,
      "end": 3
    },
    {
      "word": "فَسُحْقًا",
      "start": 3,
      "end": 4.5
    },
    {
      "word": "لِّأَصْحَٰبِ",
      "start": 4.5,
      "end": 6
    },
    {
      "word": "ٱلسَّعِيرِ",
      "start": 6,
      "end": 7.5
    }
  ],
  "12": [
    {
      "word": "إِنَّ",
      "start": 0.14,
      "end": 1.38
    },
    {
      "word": "ٱلَّذِينَ",
      "start": 1.38,
      "end": 2.61
    },
    {
      "word": "يَخْشَوْنَ",
      "start": 2.61,
      "end": 3.85
    },
    {
      "word": "رَبَّهُم",
      "start": 3.85,
      "end": 5.08
    },
    {
      "word": "بِٱلْغَيْبِ",
      "start": 5.08,
      "end": 6.32
    },
    {
      "word": "لَهُم",
      "start": 6.32,
      "end": 7.55
    },
    {
      "word": "مَّغْفِرَةٌ",
      "start": 7.55,
      "end": 8.79
    },
    {
      "word": "وَأَجْرٌ",
      "start": 8.79,
      "end": 10.02
    },
    {
      "word": "كَبِيرٌ",
      "start": 10.02,
      "end": 11.26
    }
  ],
  "13": [
    {
      "word": "وَأَسِرُّوا۟",
      "start": 0.2,
      "end": 1.43
    },
    {
      "word": "قَوْلَكُمْ",
      "start": 1.43,
      "end": 2.66
    },
    {
      "word": "أَوِ",
      "start": 2.66,
      "end": 3.89
    },
    {
      "word": "ٱجْهَرُوا۟",
      "start": 3.89,
      "end": 5.12
    },
    {
      "word": "بِهِۦٓ",
      "start": 5.12,
      "end": 6.36
    },
    {
      "word": "إِنَّهُۥ",
      "start": 6.36,
      "end": 7.59
    },
    {
      "word": "عَلِيمٌۢ",
      "start": 7.59,
      "end": 8.82
    },
    {
      "word": "بِذَاتِ",
      "start": 8.82,
      "end": 10.05
    },
    {
      "word": "ٱلصُّدُورِ",
      "start": 10.05,
      "end": 11.28
    }
  ],
  "14": [
    {
      "word": "أَلَا",
      "start": 0,
      "end": 0.94
    },
    {
      "word": "يَعْلَمُ",
      "start": 0.94,
      "end": 1.87
    },
    {
      "word": "مَنْ",
      "start": 1.87,
      "end": 2.81
    },
    {
      "word": "خَلَقَ",
      "start": 2.81,
      "end": 3.75
    },
    {
      "word": "وَهُوَ",
      "start": 3.75,
      "end": 4.69
    },
    {
      "word": "ٱللَّطِيفُ",
      "start": 4.69,
      "end": 5.62
    },
    {
      "word": "ٱلْخَبِيرُ",
      "start": 5.62,
      "end": 6.56
    }
  ],
  "15": [
    {
      "word": "هُوَ",
      "start": 0,
      "end": 1
    },
    {
      "word": "ٱلَّذِى",
      "start": 1,
      "end": 2.01
    },
    {
      "word": "جَعَلَ",
      "start": 2.01,
      "end": 3.01
    },
    {
      "word": "لَكُمُ",
      "start": 3.01,
      "end": 4.01
    },
    {
      "word": "ٱلْأَرْضَ",
      "start": 4.01,
      "end": 5.01
    },
    {
      "word": "ذَلُولًا",
      "start": 5.01,
      "end": 6.02
    },
    {
      "word": "فَٱمْشُوا۟",
      "start": 6.02,
      "end": 7.02
    },
    {
      "word": "فِى",
      "start": 7.02,
      "end": 8.02
    },
    {
      "word": "مَنَاكِبِهَا",
      "start": 8.02,
      "end": 9.03
    },
    {
      "word": "وَكُلُوا۟",
      "start": 9.03,
      "end": 10.03
    },
    {
      "word": "مِن",
      "start": 10.03,
      "end": 11.03
    },
    {
      "word": "رِّزْقِهِۦ",
      "start": 11.03,
      "end": 12.03
    },
    {
      "word": "وَإِلَيْهِ",
      "start": 12.03,
      "end": 13.04
    },
    {
      "word": "ٱلنُّشُورُ",
      "start": 13.04,
      "end": 14.04
    }
  ],
  "16": [
    {
      "word": "ءَأَمِنتُم",
      "start": 0,
      "end": 0.92
    },
    {
      "word": "مَّن",
      "start": 0.92,
      "end": 1.84
    },
    {
      "word": "فِى",
      "start": 1.84,
      "end": 2.77
    },
    {
      "word": "ٱلسَّمَآءِ",
      "start": 2.77,
      "end": 3.69
    },
    {
      "word": "أَن",
      "start": 3.69,
      "end": 4.61
    },
    {
      "word": "يَخْسِفَ",
      "start": 4.61,
      "end": 5.53
    },
    {
      "word": "بِكُمُ",
      "start": 5.53,
      "end": 6.45
    },
    {
      "word": "ٱلْأَرْضَ",
      "start": 6.45,
      "end": 7.37
    },
    {
      "word": "فَإِذَا",
      "start": 7.37,
      "end": 8.3
    },
    {
      "word": "هِىَ",
      "start": 8.3,
      "end": 9.22
    },
    {
      "word": "تَمُورُ",
      "start": 9.22,
      "end": 10.14
    }
  ],
  "17": [
    {
      "word": "أَمْ",
      "start": 0,
      "end": 1.12
    },
    {
      "word": "أَمِنتُم",
      "start": 1.12,
      "end": 2.23
    },
    {
      "word": "مَّن",
      "start": 2.23,
      "end": 3.35
    },
    {
      "word": "فِى",
      "start": 3.35,
      "end": 4.47
    },
    {
      "word": "ٱلسَّمَآءِ",
      "start": 4.47,
      "end": 5.58
    },
    {
      "word": "أَن",
      "start": 5.58,
      "end": 6.7
    },
    {
      "word": "يُرْسِلَ",
      "start": 6.7,
      "end": 7.82
    },
    {
      "word": "عَلَيْكُمْ",
      "start": 7.82,
      "end": 8.93
    },
    {
      "word": "حَاصِبًا",
      "start": 8.93,
      "end": 10.05
    },
    {
      "word": "فَسَتَعْلَمُونَ",
      "start": 10.05,
      "end": 11.17
    },
    {
      "word": "كَيْفَ",
      "start": 11.17,
      "end": 12.28
    },
    {
      "word": "نَذِيرِ",
      "start": 12.28,
      "end": 13.4
    }
  ],
  "18": [
    {
      "word": "وَلَقَدْ",
      "start": 0,
      "end": 1.01
    },
    {
      "word": "كَذَّبَ",
      "start": 1.01,
      "end": 2.03
    },
    {
      "word": "ٱلَّذِينَ",
      "start": 2.03,
      "end": 3.04
    },
    {
      "word": "مِن",
      "start": 3.04,
      "end": 4.05
    },
    {
      "word": "قَبْلِهِمْ",
      "start": 4.05,
      "end": 5.06
    },
    {
      "word": "فَكَيْفَ",
      "start": 5.06,
      "end": 6.07
    },
    {
      "word": "كَانَ",
      "start": 6.07,
      "end": 7.09
    },
    {
      "word": "نَكِيرِ",
      "start": 7.09,
      "end": 8.1
    }
  ],
  "19": [
    {
      "word": "أَوَلَمْ",
      "start": 0.12,
      "end": 1.49
    },
    {
      "word": "يَرَوْا۟",
      "start": 1.49,
      "end": 2.86
    },
    {
      "word": "إِلَى",
      "start": 2.86,
      "end": 4.23
    },
    {
      "word": "ٱلطَّيْرِ",
      "start": 4.23,
      "end": 5.6
    },
    {
      "word": "فَوْقَهُمْ",
      "start": 5.6,
      "end": 6.97
    },
    {
      "word": "صَٰٓفَّٰتٍ",
      "start": 6.97,
      "end": 8.34
    },
    {
      "word": "وَيَقْبِضْنَ",
      "start": 8.34,
      "end": 9.71
    },
    {
      "word": "مَا",
      "start": 9.71,
      "end": 11.09
    },
    {
      "word": "يُمْسِكُهُنَّ",
      "start": 11.09,
      "end": 12.46
    },
    {
      "word": "إِلَّا",
      "start": 12.46,
      "end": 13.83
    },
    {
      "word": "ٱلرَّحْمَٰنُ",
      "start": 13.83,
      "end": 15.2
    },
    {
      "word": "إِنَّهُۥ",
      "start": 15.2,
      "end": 16.57
    },
    {
      "word": "بِكُلِّ",
      "start": 16.57,
      "end": 17.94
    },
    {
      "word": "شَىْءٍۭ",
      "start": 17.94,
      "end": 19.31
    },
    {
      "word": "بَصِيرٌ",
      "start": 19.31,
      "end": 20.68
    }
  ],
  "20": [
    {
      "word": "أَمَّنْ",
      "start": 0.3,
      "end": 1.41
    },
    {
      "word": "هَٰذَا",
      "start": 1.41,
      "end": 2.53
    },
    {
      "word": "ٱلَّذِى",
      "start": 2.53,
      "end": 3.64
    },
    {
      "word": "هُوَ",
      "start": 3.64,
      "end": 4.76
    },
    {
      "word": "جُندٌ",
      "start": 4.76,
      "end": 5.87
    },
    {
      "word": "لَّكُمْ",
      "start": 5.87,
      "end": 6.99
    },
    {
      "word": "يَنصُرُكُم",
      "start": 6.99,
      "end": 8.1
    },
    {
      "word": "مِّن",
      "start": 8.1,
      "end": 9.22
    },
    {
      "word": "دُونِ",
      "start": 9.22,
      "end": 10.33
    },
    {
      "word": "ٱلرَّحْمَٰنِ",
      "start": 10.33,
      "end": 11.45
    },
    {
      "word": "إِنِ",
      "start": 11.45,
      "end": 12.56
    },
    {
      "word": "ٱلْكَٰفِرُونَ",
      "start": 12.56,
      "end": 13.68
    },
    {
      "word": "إِلَّا",
      "start": 13.68,
      "end": 14.79
    },
    {
      "word": "فِى",
      "start": 14.79,
      "end": 15.91
    },
    {
      "word": "غُرُورٍ",
      "start": 15.91,
      "end": 17.02
    }
  ],
  "21": [
    {
      "word": "أَمَّنْ",
      "start": 0,
      "end": 1.06
    },
    {
      "word": "هَٰذَا",
      "start": 1.06,
      "end": 2.12
    },
    {
      "word": "ٱلَّذِى",
      "start": 2.12,
      "end": 3.18
    },
    {
      "word": "يَرْزُقُكُمْ",
      "start": 3.18,
      "end": 4.23
    },
    {
      "word": "إِنْ",
      "start": 4.23,
      "end": 5.29
    },
    {
      "word": "أَمْسَكَ",
      "start": 5.29,
      "end": 6.35
    },
    {
      "word": "رِزْقَهُۥ",
      "start": 6.35,
      "end": 7.41
    },
    {
      "word": "بَل",
      "start": 7.41,
      "end": 8.47
    },
    {
      "word": "لَّجُّوا۟",
      "start": 8.47,
      "end": 9.53
    },
    {
      "word": "فِى",
      "start": 9.53,
      "end": 10.58
    },
    {
      "word": "عُتُوٍّ",
      "start": 10.58,
      "end": 11.64
    },
    {
      "word": "وَنُفُورٍ",
      "start": 11.64,
      "end": 12.7
    }
  ],
  "22": [
    {
      "word": "أَفَمَن",
      "start": 0.2,
      "end": 1.02
    },
    {
      "word": "يَمْشِى",
      "start": 1.02,
      "end": 1.83
    },
    {
      "word": "مُكِبًّا",
      "start": 1.83,
      "end": 2.65
    },
    {
      "word": "عَلَىٰ",
      "start": 2.65,
      "end": 3.46
    },
    {
      "word": "وَجْهِهِۦٓ",
      "start": 3.46,
      "end": 4.28
    },
    {
      "word": "أَهْدَىٰٓ",
      "start": 4.28,
      "end": 5.09
    },
    {
      "word": "أَمَّن",
      "start": 5.09,
      "end": 5.91
    },
    {
      "word": "يَمْشِى",
      "start": 5.91,
      "end": 6.72
    },
    {
      "word": "سَوِيًّا",
      "start": 6.72,
      "end": 7.54
    },
    {
      "word": "عَلَىٰ",
      "start": 7.54,
      "end": 8.35
    },
    {
      "word": "صِرَٰطٍ",
      "start": 8.35,
      "end": 9.16
    },
    {
      "word": "مُّسْتَقِيمٍ",
      "start": 9.16,
      "end": 9.98
    }
  ],
  "23": [
    {
      "word": "قُلْ",
      "start": 0,
      "end": 1.17
    },
    {
      "word": "هُوَ",
      "start": 1.17,
      "end": 2.33
    },
    {
      "word": "ٱلَّذِىٓ",
      "start": 2.33,
      "end": 3.5
    },
    {
      "word": "أَنشَأَكُمْ",
      "start": 3.5,
      "end": 4.66
    },
    {
      "word": "وَجَعَلَ",
      "start": 4.66,
      "end": 5.83
    },
    {
      "word": "لَكُمُ",
      "start": 5.83,
      "end": 6.99
    },
    {
      "word": "ٱلسَّمْعَ",
      "start": 6.99,
      "end": 8.16
    },
    {
      "word": "وَٱلْأَبْصَٰرَ",
      "start": 8.16,
      "end": 9.32
    },
    {
      "word": "وَٱلْأَفْـِٔدَةَ",
      "start": 9.32,
      "end": 10.49
    },
    {
      "word": "قَلِيلًا",
      "start": 10.49,
      "end": 11.65
    },
    {
      "word": "مَّا",
      "start": 11.65,
      "end": 12.82
    },
    {
      "word": "تَشْكُرُونَ",
      "start": 12.82,
      "end": 13.98
    }
  ],
  "24": [
    {
      "word": "قُلْ",
      "start": 0,
      "end": 0.92
    },
    {
      "word": "هُوَ",
      "start": 0.92,
      "end": 1.85
    },
    {
      "word": "ٱلَّذِى",
      "start": 1.85,
      "end": 2.77
    },
    {
      "word": "ذَرَأَكُمْ",
      "start": 2.77,
      "end": 3.69
    },
    {
      "word": "فِى",
      "start": 3.69,
      "end": 4.61
    },
    {
      "word": "ٱلْأَرْضِ",
      "start": 4.61,
      "end": 5.54
    },
    {
      "word": "وَإِلَيْهِ",
      "start": 5.54,
      "end": 6.46
    },
    {
      "word": "تُحْشَرُونَ",
      "start": 6.46,
      "end": 7.38
    }
  ],
  "25": [
    {
      "word": "وَيَقُولُونَ",
      "start": 0,
      "end": 1.21
    },
    {
      "word": "مَتَىٰ",
      "start": 1.21,
      "end": 2.42
    },
    {
      "word": "هَٰذَا",
      "start": 2.42,
      "end": 3.63
    },
    {
      "word": "ٱلْوَعْدُ",
      "start": 3.63,
      "end": 4.83
    },
    {
      "word": "إِن",
      "start": 4.83,
      "end": 6.04
    },
    {
      "word": "كُنتُمْ",
      "start": 6.04,
      "end": 7.25
    },
    {
      "word": "صَٰدِقِينَ",
      "start": 7.25,
      "end": 8.46
    }
  ],
  "26": [
    {
      "word": "قُلْ",
      "start": 0,
      "end": 1.1
    },
    {
      "word": "إِنَّمَا",
      "start": 1.1,
      "end": 2.19
    },
    {
      "word": "ٱلْعِلْمُ",
      "start": 2.19,
      "end": 3.29
    },
    {
      "word": "عِندَ",
      "start": 3.29,
      "end": 4.38
    },
    {
      "word": "ٱللَّهِ",
      "start": 4.38,
      "end": 5.48
    },
    {
      "word": "وَإِنَّمَآ",
      "start": 5.48,
      "end": 6.57
    },
    {
      "word": "أَنَا۠",
      "start": 6.57,
      "end": 7.67
    },
    {
      "word": "نَذِيرٌ",
      "start": 7.67,
      "end": 8.76
    },
    {
      "word": "مُّبِينٌ",
      "start": 8.76,
      "end": 9.86
    }
  ],
  "27": [
    {
      "word": "فَلَمَّا",
      "start": 0,
      "end": 1.34
    },
    {
      "word": "رَأَوْهُ",
      "start": 1.34,
      "end": 2.69
    },
    {
      "word": "زُلْفَةً",
      "start": 2.69,
      "end": 4.03
    },
    {
      "word": "سِيٓـَٔتْ",
      "start": 4.03,
      "end": 5.38
    },
    {
      "word": "وُجُوهُ",
      "start": 5.38,
      "end": 6.72
    },
    {
      "word": "ٱلَّذِينَ",
      "start": 6.72,
      "end": 8.07
    },
    {
      "word": "كَفَرُوا۟",
      "start": 8.07,
      "end": 9.41
    },
    {
      "word": "وَقِيلَ",
      "start": 9.41,
      "end": 10.76
    },
    {
      "word": "هَٰذَا",
      "start": 10.76,
      "end": 12.1
    },
    {
      "word": "ٱلَّذِى",
      "start": 12.1,
      "end": 13.45
    },
    {
      "word": "كُنتُم",
      "start": 13.45,
      "end": 14.79
    },
    {
      "word": "بِهِۦ",
      "start": 14.79,
      "end": 16.14
    },
    {
      "word": "تَدَّعُونَ",
      "start": 16.14,
      "end": 17.48
    }
  ],
  "28": [
    {
      "word": "قُلْ",
      "start": 0.12,
      "end": 1.1
    },
    {
      "word": "أَرَءَيْتُمْ",
      "start": 1.1,
      "end": 2.08
    },
    {
      "word": "إِنْ",
      "start": 2.08,
      "end": 3.06
    },
    {
      "word": "أَهْلَكَنِىَ",
      "start": 3.06,
      "end": 4.04
    },
    {
      "word": "ٱللَّهُ",
      "start": 4.04,
      "end": 5.02
    },
    {
      "word": "وَمَن",
      "start": 5.02,
      "end": 6
    },
    {
      "word": "مَّعِىَ",
      "start": 6,
      "end": 6.98
    },
    {
      "word": "أَوْ",
      "start": 6.98,
      "end": 7.96
    },
    {
      "word": "رَحِمَنَا",
      "start": 7.96,
      "end": 8.94
    },
    {
      "word": "فَمَن",
      "start": 8.94,
      "end": 9.92
    },
    {
      "word": "يُجِيرُ",
      "start": 9.92,
      "end": 10.9
    },
    {
      "word": "ٱلْكَٰفِرِينَ",
      "start": 10.9,
      "end": 11.88
    },
    {
      "word": "مِنْ",
      "start": 11.88,
      "end": 12.86
    },
    {
      "word": "عَذَابٍ",
      "start": 12.86,
      "end": 13.84
    },
    {
      "word": "أَلِيمٍ",
      "start": 13.84,
      "end": 14.82
    }
  ],
  "29": [
    {
      "word": "قُلْ",
      "start": 0.16,
      "end": 1.26
    },
    {
      "word": "هُوَ",
      "start": 1.26,
      "end": 2.36
    },
    {
      "word": "ٱلرَّحْمَٰنُ",
      "start": 2.36,
      "end": 3.46
    },
    {
      "word": "ءَامَنَّا",
      "start": 3.46,
      "end": 4.56
    },
    {
      "word": "بِهِۦ",
      "start": 4.56,
      "end": 5.66
    },
    {
      "word": "وَعَلَيْهِ",
      "start": 5.66,
      "end": 6.76
    },
    {
      "word": "تَوَكَّلْنَا",
      "start": 6.76,
      "end": 7.86
    },
    {
      "word": "فَسَتَعْلَمُونَ",
      "start": 7.86,
      "end": 8.96
    },
    {
      "word": "مَنْ",
      "start": 8.96,
      "end": 10.06
    },
    {
      "word": "هُوَ",
      "start": 10.06,
      "end": 11.16
    },
    {
      "word": "فِى",
      "start": 11.16,
      "end": 12.26
    },
    {
      "word": "ضَلَٰلٍ",
      "start": 12.26,
      "end": 13.36
    },
    {
      "word": "مُّبِينٍ",
      "start": 13.36,
      "end": 14.46
    }
  ],
  "30": [
    {
      "word": "قُلْ",
      "start": 0.14,
      "end": 1.61
    },
    {
      "word": "أَرَءَيْتُمْ",
      "start": 1.61,
      "end": 3.08
    },
    {
      "word": "إِنْ",
      "start": 3.08,
      "end": 4.54
    },
    {
      "word": "أَصْبَحَ",
      "start": 4.54,
      "end": 6.01
    },
    {
      "word": "مَآؤُكُمْ",
      "start": 6.01,
      "end": 7.48
    },
    {
      "word": "غَوْرًا",
      "start": 7.48,
      "end": 8.95
    },
    {
      "word": "فَمَن",
      "start": 8.95,
      "end": 10.42
    },
    {
      "word": "يَأْتِيكُم",
      "start": 10.42,
      "end": 11.88
    },
    {
      "word": "بِمَآءٍ",
      "start": 11.88,
      "end": 13.35
    },
    {
      "word": "مَّعِينٍۭ",
      "start": 13.35,
      "end": 14.82
    }
  ]
}